JS_py/Build/Buildtools.py
JS_py/Build/Parser.py
JS_py/__main__.py
js_fpy/JS-py.py
js_fpy/__init__.py
js_fpy-0.1.4.dist-info/WHEEL
js_fpy-0.1.4.dist-info/METADATA
js_fpy-0.1.4.dist-info/RECORD
